[{"level":1,"points_to_gain":0,"points_per_click":1},{"level":2,"points_to_gain":12,"points_per_click":2},{"level":3,"points_to_gain":30,"points_per_click":5},{"level":4,"points_to_gain":70,"points_per_click":7},{"level":5,"points_to_gain":150,"points_per_click":10},{"level":6,"points_to_gain":250,"points_per_click":12},{"level":7,"points_to_gain":350,"points_per_click":15},{"level":8,"points_to_gain":500,"points_per_click":20},{"level":9,"points_to_gain":700,"points_per_click":24},{"level":10,"points_to_gain":1000,"points_per_click":27},{"level":11,"points_to_gain":1500,"points_per_click":31},{"level":12,"points_to_gain":2300,"points_per_click":32},{"level":13,"points_to_gain":3000,"points_per_click":35}]